AUTHORS.rst
CHANGES.rst
LICENSE
MANIFEST.in
README.rst
setup.py
s3keyring/__init__.py
s3keyring/cli.py
s3keyring/s3.py
s3keyring/s3keyring.ini
s3keyring/settings.py
s3keyring.egg-info/PKG-INFO
s3keyring.egg-info/SOURCES.txt
s3keyring.egg-info/dependency_links.txt
s3keyring.egg-info/entry_points.txt
s3keyring.egg-info/not-zip-safe
s3keyring.egg-info/requires.txt
s3keyring.egg-info/top_level.txt