Metadata-Version: 1.1
Name: s3keyring
Version: 0.2.2
Summary: S3 backend for Python's keyring module
Home-page: http://github.com/findhotel/s3keyring
Author: German Gomez-Herrero
Author-email: data@findhotel.net
License: MIT
Platform: UNKNOWN
Classifier: Programming Language :: Python :: 2
Classifier: Programming Language :: Python :: 3
